bc.py
bc_1922053.py
bc_1922053-0.0.1.dist-info/METADATA
bc_1922053-0.0.1.dist-info/WHEEL
bc_1922053-0.0.1.dist-info/entry_points.txt
bc_1922053-0.0.1.dist-info/top_level.txt
bc_1922053-0.0.1.dist-info/RECORD
