Metadata-Version: 2.1
Name: bc-1922053
Version: 0.0.1
Summary: Brand identification
Home-page: UNKNOWN
Author: yuta icchikawa
Author-email: s1922053@stu.musashino-u.ac.jp
License: UNKNOWN
Platform: UNKNOWN
Classifier: Programming Language :: Python :: 3
Requires-Python: >=3.6
